<?xml version = '1.0' encoding = 'UTF-8'?>
<Diagram class="oracle.dbtools.crest.swingui.logical.DPVLogical" name="Logical" id="DF0BBAEC-71C9-3B18-90E4-64AF92B7C109">
<createdBy>ADmiN</createdBy>
<modifiedBy>ADmiN</modifiedBy>
<createdTime>2025-08-10 16:06:17 UTC</createdTime>
<autoRoute>false</autoRoute>
<boxInbox>true</boxInbox>
<showLegend>false</showLegend>
<showLabels>false</showLabels>
<showRelAttributes>false</showRelAttributes>
<gridEnabled>false</gridEnabled>
<showGrid>false</showGrid>
<diagramColor>-1</diagramColor>
<display>false</display>
<notation>1</notation>
<objectViews>
<OView class="oracle.dbtools.crest.swingui.logical.TVEntity" oid="04439F7B-E4CA-4F15-013D-BFA2D3C02F40" otype="Entity" vid="629910AB-2CAA-80E9-64BB-2C0BD30D35A3">
<hideElementsInCurrentOnly>false</hideElementsInCurrentOnly>
<bounds x="462" y="189" width="93" height="92"/>
</OView>
<OView class="oracle.dbtools.crest.swingui.logical.TVEntity" oid="174AAC56-D833-C268-A2E8-A1014EBCD9E7" otype="Entity" vid="C5AD0DDA-96C8-8120-C835-5471AFFB99C6">
<hideElementsInCurrentOnly>false</hideElementsInCurrentOnly>
<bounds x="763" y="309" width="92" height="76"/>
</OView>
<OView class="oracle.dbtools.crest.swingui.logical.TVEntity" oid="1C187650-F293-53E8-3463-67DCE9A308BD" otype="Entity" vid="40E45563-6484-4ECE-F5E1-A0B47B264D4D">
<hideElementsInCurrentOnly>false</hideElementsInCurrentOnly>
<bounds x="854" y="200" width="99" height="90"/>
</OView>
<OView class="oracle.dbtools.crest.swingui.logical.TVEntity" oid="1DCE1EFC-2880-5D59-FDBD-841619ABD55E" otype="Entity" vid="0E6C2D02-9182-4178-7BB6-1C7DCCF532F4">
<hideElementsInCurrentOnly>false</hideElementsInCurrentOnly>
<bounds x="51" y="177" width="125" height="102"/>
</OView>
<OView class="oracle.dbtools.crest.swingui.logical.TVEntity" oid="284FB61A-A468-6AD2-C659-EC05D0972EE1" otype="Entity" vid="F1781FFC-866F-C80C-C5AF-A067D241D79E">
<hideElementsInCurrentOnly>false</hideElementsInCurrentOnly>
<bounds x="809" y="31" width="170" height="158"/>
</OView>
<OView class="oracle.dbtools.crest.swingui.logical.TVEntity" oid="2C299C12-48BC-4FD8-3180-FE2E1E4CB568" otype="Entity" vid="751519FB-968C-681A-DF3C-C3147A570649">
<hideElementsInCurrentOnly>false</hideElementsInCurrentOnly>
<bounds x="463" y="36" width="100" height="110"/>
</OView>
<OView class="oracle.dbtools.crest.swingui.logical.TVEntity" oid="4B9DBE65-068D-A05C-468E-07B617D16EF1" otype="Entity" vid="4B8A29A3-F893-BA47-FC54-77FAB2AB2917">
<hideElementsInCurrentOnly>false</hideElementsInCurrentOnly>
<bounds x="586" y="184" width="118" height="80"/>
</OView>
<OView class="oracle.dbtools.crest.swingui.logical.TVEntity" oid="512EC8F4-0C06-4746-4443-15E8433E7C76" otype="Entity" vid="2BD11874-E6F9-B7FA-6405-B493CE2C64B0">
<hideElementsInCurrentOnly>false</hideElementsInCurrentOnly>
<bounds x="728" y="174" width="73" height="64"/>
</OView>
<OView class="oracle.dbtools.crest.swingui.logical.TVEntity" oid="5751A2B6-B70E-4B5C-FD66-9D20AECD9881" otype="Entity" vid="2D23CA9D-CE18-439A-5E4D-20BA21508048">
<hideElementsInCurrentOnly>false</hideElementsInCurrentOnly>
<bounds x="627" y="304" width="105" height="133"/>
</OView>
<OView class="oracle.dbtools.crest.swingui.logical.TVEntity" oid="6932A492-7D17-4A76-EB26-6C7107579742" otype="Entity" vid="9D23D99E-A10C-4C26-A1A3-DADB6AB6DCF9">
<hideElementsInCurrentOnly>false</hideElementsInCurrentOnly>
<bounds x="197" y="14" width="115" height="191"/>
</OView>
<OView class="oracle.dbtools.crest.swingui.logical.TVEntity" oid="B0D64C35-B86D-F8B4-4C35-353AFC3B2D1E" otype="Entity" vid="8039606D-8642-1F3F-8DD7-B260E0AF4FAA">
<hideElementsInCurrentOnly>false</hideElementsInCurrentOnly>
<bounds x="345" y="52" width="96" height="103"/>
</OView>
<OView class="oracle.dbtools.crest.swingui.logical.TVEntity" oid="B4C58AC5-721F-01A2-7013-52DBA9AE3071" otype="Entity" vid="ABE3A12A-3371-AF89-5509-EBDF998578DD">
<hideElementsInCurrentOnly>false</hideElementsInCurrentOnly>
<bounds x="438" y="315" width="170" height="110"/>
</OView>
<OView class="oracle.dbtools.crest.swingui.logical.TVEntity" oid="B6981843-47A2-8ECD-49F8-9342EBAE6CC2" otype="Entity" vid="B478AB2C-255A-3B5B-CBA7-8BE6F6963B86">
<hideElementsInCurrentOnly>false</hideElementsInCurrentOnly>
<bounds x="217" y="233" width="187" height="189"/>
</OView>
<OView class="oracle.dbtools.crest.swingui.logical.TVEntity" oid="C703360F-D1FD-CD07-F4DF-FFD0DF1610A9" otype="Entity" vid="03422B59-3141-2096-F87B-B3D624F94C75">
<hideElementsInCurrentOnly>false</hideElementsInCurrentOnly>
<bounds x="609" y="43" width="149" height="117"/>
</OView>
</objectViews>
<connectors>
<Connector class="oracle.dbtools.crest.swingui.logical.TVRelation" oid="08E27ECD-E0D0-4347-43CB-3551AED5C1BD" otype="Relation" vid_source="8039606D-8642-1F3F-8DD7-B260E0AF4FAA" vid_target="F1781FFC-866F-C80C-C5AF-A067D241D79E">
<hideElementsInCurrentOnly>false</hideElementsInCurrentOnly>
<backgroundColor>-16777216</backgroundColor>
<lineWidth>1</lineWidth>
<points>
<point x="441" y="103"/>
<point x="809" y="103"/>
</points>
</Connector>
<Connector class="oracle.dbtools.crest.swingui.logical.TVRelation" oid="1BAA98A2-8E3D-F298-CC9A-57110399276A" otype="Relation" vid_source="F1781FFC-866F-C80C-C5AF-A067D241D79E" vid_target="B478AB2C-255A-3B5B-CBA7-8BE6F6963B86">
<hideElementsInCurrentOnly>false</hideElementsInCurrentOnly>
<backgroundColor>-16777216</backgroundColor>
<lineWidth>1</lineWidth>
<points>
<point x="809" y="141"/>
<point x="404" y="292"/>
</points>
</Connector>
<Connector class="oracle.dbtools.crest.swingui.logical.TVRelation" oid="2118A1CC-D614-C335-DBDC-85F87DF115D5" otype="Relation" vid_source="9D23D99E-A10C-4C26-A1A3-DADB6AB6DCF9" vid_target="B478AB2C-255A-3B5B-CBA7-8BE6F6963B86">
<hideElementsInCurrentOnly>false</hideElementsInCurrentOnly>
<backgroundColor>-16777216</backgroundColor>
<lineWidth>1</lineWidth>
<points>
<point x="264" y="205"/>
<point x="264" y="233"/>
</points>
</Connector>
<Connector class="oracle.dbtools.crest.swingui.logical.TVRelation" oid="69F7DD53-62D3-2179-FAB0-60A91497DE63" otype="Relation" vid_source="9D23D99E-A10C-4C26-A1A3-DADB6AB6DCF9" vid_target="4B8A29A3-F893-BA47-FC54-77FAB2AB2917">
<hideElementsInCurrentOnly>false</hideElementsInCurrentOnly>
<backgroundColor>-16777216</backgroundColor>
<lineWidth>1</lineWidth>
<points>
<point x="312" y="194"/>
<point x="586" y="194"/>
</points>
</Connector>
<Connector class="oracle.dbtools.crest.swingui.logical.TVRelation" oid="6D0C7BE4-8DE9-16D3-65CF-75E7F253E237" otype="Relation" vid_source="2D23CA9D-CE18-439A-5E4D-20BA21508048" vid_target="2BD11874-E6F9-B7FA-6405-B493CE2C64B0">
<hideElementsInCurrentOnly>false</hideElementsInCurrentOnly>
<backgroundColor>-16777216</backgroundColor>
<lineWidth>1</lineWidth>
<points>
<point x="730" y="304"/>
<point x="730" y="238"/>
</points>
</Connector>
<Connector class="oracle.dbtools.crest.swingui.logical.TVRelation" oid="829EB1FE-7333-70F8-5BB1-3ECC9B4C53C5" otype="Relation" vid_source="8039606D-8642-1F3F-8DD7-B260E0AF4FAA" vid_target="751519FB-968C-681A-DF3C-C3147A570649">
<hideElementsInCurrentOnly>false</hideElementsInCurrentOnly>
<backgroundColor>-16777216</backgroundColor>
<lineWidth>1</lineWidth>
<points>
<point x="441" y="84"/>
<point x="463" y="84"/>
</points>
</Connector>
<Connector class="oracle.dbtools.crest.swingui.logical.TVRelation" oid="83CF72B6-F78D-D19B-BDF5-43CEAE0FAE3C" otype="Relation" vid_source="9D23D99E-A10C-4C26-A1A3-DADB6AB6DCF9" vid_target="2D23CA9D-CE18-439A-5E4D-20BA21508048">
<hideElementsInCurrentOnly>false</hideElementsInCurrentOnly>
<backgroundColor>-16777216</backgroundColor>
<lineWidth>1</lineWidth>
<points>
<point x="312" y="144"/>
<point x="627" y="353"/>
</points>
</Connector>
<Connector class="oracle.dbtools.crest.swingui.logical.TVRelation" oid="8945E7E3-D641-B7FA-5E29-159FE11FE711" otype="Relation" vid_source="B478AB2C-255A-3B5B-CBA7-8BE6F6963B86" vid_target="ABE3A12A-3371-AF89-5509-EBDF998578DD">
<hideElementsInCurrentOnly>false</hideElementsInCurrentOnly>
<backgroundColor>-16777216</backgroundColor>
<lineWidth>1</lineWidth>
<points>
<point x="404" y="368"/>
<point x="438" y="368"/>
</points>
</Connector>
<Connector class="oracle.dbtools.crest.swingui.logical.TVRelation" oid="9008F00D-5F27-1D47-31AF-55CA2089A4C2" otype="Relation" vid_source="8039606D-8642-1F3F-8DD7-B260E0AF4FAA" vid_target="2BD11874-E6F9-B7FA-6405-B493CE2C64B0">
<hideElementsInCurrentOnly>false</hideElementsInCurrentOnly>
<backgroundColor>-16777216</backgroundColor>
<lineWidth>1</lineWidth>
<points>
<point x="441" y="116"/>
<point x="728" y="195"/>
</points>
</Connector>
<Connector class="oracle.dbtools.crest.swingui.logical.TVRelation" oid="9331C541-A81A-B6F9-AF8C-29678CD73B09" otype="Relation" vid_source="8039606D-8642-1F3F-8DD7-B260E0AF4FAA" vid_target="C5AD0DDA-96C8-8120-C835-5471AFFB99C6">
<hideElementsInCurrentOnly>false</hideElementsInCurrentOnly>
<backgroundColor>-16777216</backgroundColor>
<lineWidth>1</lineWidth>
<points>
<point x="441" y="131"/>
<point x="763" y="320"/>
</points>
</Connector>
<Connector class="oracle.dbtools.crest.swingui.logical.TVRelation" oid="94776EC1-91AD-5B43-0C47-586540AABE4C" otype="Relation" vid_source="751519FB-968C-681A-DF3C-C3147A570649" vid_target="4B8A29A3-F893-BA47-FC54-77FAB2AB2917">
<hideElementsInCurrentOnly>false</hideElementsInCurrentOnly>
<backgroundColor>-16777216</backgroundColor>
<lineWidth>1</lineWidth>
<points>
<point x="563" y="141"/>
<point x="605" y="184"/>
</points>
</Connector>
<Connector class="oracle.dbtools.crest.swingui.logical.TVRelation" oid="AB1A6A27-5539-D5DE-A52B-1F90AEC131B3" otype="Relation" vid_source="2D23CA9D-CE18-439A-5E4D-20BA21508048" vid_target="40E45563-6484-4ECE-F5E1-A0B47B264D4D">
<hideElementsInCurrentOnly>false</hideElementsInCurrentOnly>
<backgroundColor>-16777216</backgroundColor>
<lineWidth>1</lineWidth>
<points>
<point x="732" y="341"/>
<point x="854" y="272"/>
</points>
</Connector>
<Connector class="oracle.dbtools.crest.swingui.logical.TVRelation" oid="CABA8731-6D3F-181B-8B7F-9EE85610A764" otype="Relation" vid_source="8039606D-8642-1F3F-8DD7-B260E0AF4FAA" vid_target="03422B59-3141-2096-F87B-B3D624F94C75">
<hideElementsInCurrentOnly>false</hideElementsInCurrentOnly>
<backgroundColor>-16777216</backgroundColor>
<lineWidth>1</lineWidth>
<points>
<point x="441" y="58"/>
<point x="609" y="58"/>
</points>
</Connector>
<Connector class="oracle.dbtools.crest.swingui.logical.TVRelation" oid="CD07F3D4-6EC5-1B2F-3788-DFEBE91C8EE8" otype="Relation" vid_source="B478AB2C-255A-3B5B-CBA7-8BE6F6963B86" vid_target="8039606D-8642-1F3F-8DD7-B260E0AF4FAA">
<hideElementsInCurrentOnly>false</hideElementsInCurrentOnly>
<backgroundColor>-16777216</backgroundColor>
<lineWidth>1</lineWidth>
<points>
<point x="374" y="233"/>
<point x="374" y="155"/>
</points>
</Connector>
<Connector class="oracle.dbtools.crest.swingui.logical.TVRelation" oid="CDF6362A-7216-6833-4993-C4937FB18923" otype="Relation" vid_source="8039606D-8642-1F3F-8DD7-B260E0AF4FAA" vid_target="629910AB-2CAA-80E9-64BB-2C0BD30D35A3">
<hideElementsInCurrentOnly>false</hideElementsInCurrentOnly>
<backgroundColor>-16777216</backgroundColor>
<lineWidth>1</lineWidth>
<points>
<point x="438" y="155"/>
<point x="468" y="189"/>
</points>
</Connector>
<Connector class="oracle.dbtools.crest.swingui.logical.TVRelation" oid="D44FFB1F-3751-6C69-2AB2-201967383B93" otype="Relation" vid_source="B478AB2C-255A-3B5B-CBA7-8BE6F6963B86" vid_target="0E6C2D02-9182-4178-7BB6-1C7DCCF532F4">
<hideElementsInCurrentOnly>false</hideElementsInCurrentOnly>
<backgroundColor>-16777216</backgroundColor>
<lineWidth>1</lineWidth>
<points>
<point x="217" y="256"/>
<point x="176" y="256"/>
</points>
</Connector>
<Connector class="oracle.dbtools.crest.swingui.logical.TVRelation" oid="D92F044F-A788-262D-768B-05A26EFF4729" otype="Relation" vid_source="03422B59-3141-2096-F87B-B3D624F94C75" vid_target="751519FB-968C-681A-DF3C-C3147A570649">
<hideElementsInCurrentOnly>false</hideElementsInCurrentOnly>
<backgroundColor>-16777216</backgroundColor>
<lineWidth>1</lineWidth>
<points>
<point x="609" y="94"/>
<point x="563" y="94"/>
</points>
</Connector>
<Connector class="oracle.dbtools.crest.swingui.logical.TVRelation" oid="E323F825-AEE8-5070-5F64-93546CE4CB60" otype="Relation" vid_source="40E45563-6484-4ECE-F5E1-A0B47B264D4D" vid_target="2BD11874-E6F9-B7FA-6405-B493CE2C64B0">
<hideElementsInCurrentOnly>false</hideElementsInCurrentOnly>
<backgroundColor>-16777216</backgroundColor>
<lineWidth>1</lineWidth>
<points>
<point x="854" y="219"/>
<point x="801" y="219"/>
</points>
</Connector>
<Connector class="oracle.dbtools.crest.swingui.logical.TVRelation" oid="E6668220-B243-0829-23D6-41C694584D93" otype="Relation" vid_source="8039606D-8642-1F3F-8DD7-B260E0AF4FAA" vid_target="9D23D99E-A10C-4C26-A1A3-DADB6AB6DCF9">
<hideElementsInCurrentOnly>false</hideElementsInCurrentOnly>
<backgroundColor>-16777216</backgroundColor>
<lineWidth>1</lineWidth>
<points>
<point x="345" y="118"/>
<point x="312" y="118"/>
</points>
</Connector>
<Connector class="oracle.dbtools.crest.swingui.logical.TVRelation" oid="E9CE6AA2-E1F0-F699-8266-FB0360D76871" otype="Relation" vid_source="2BD11874-E6F9-B7FA-6405-B493CE2C64B0" vid_target="C5AD0DDA-96C8-8120-C835-5471AFFB99C6">
<hideElementsInCurrentOnly>false</hideElementsInCurrentOnly>
<backgroundColor>-16777216</backgroundColor>
<lineWidth>1</lineWidth>
<points>
<point x="782" y="238"/>
<point x="782" y="309"/>
</points>
</Connector>
<Connector class="oracle.dbtools.crest.swingui.logical.TVRelation" oid="EB861D21-3753-1214-80B2-B3A6F45CF2BF" otype="Relation" vid_source="2D23CA9D-CE18-439A-5E4D-20BA21508048" vid_target="4B8A29A3-F893-BA47-FC54-77FAB2AB2917">
<hideElementsInCurrentOnly>false</hideElementsInCurrentOnly>
<backgroundColor>-16777216</backgroundColor>
<lineWidth>1</lineWidth>
<points>
<point x="665" y="304"/>
<point x="665" y="264"/>
</points>
</Connector>
<Connector class="oracle.dbtools.crest.swingui.logical.TVRelation" oid="FEF62CC7-992B-683F-E8EA-DD69F5EB4A85" otype="Relation" vid_source="8039606D-8642-1F3F-8DD7-B260E0AF4FAA" vid_target="4B8A29A3-F893-BA47-FC54-77FAB2AB2917">
<hideElementsInCurrentOnly>false</hideElementsInCurrentOnly>
<backgroundColor>-16777216</backgroundColor>
<lineWidth>1</lineWidth>
<points>
<point x="441" y="126"/>
<point x="586" y="210"/>
</points>
</Connector>
</connectors>
</Diagram>
